MANIFEST.in
README.md
setup.py
django_servee_uploadify.egg-info/PKG-INFO
django_servee_uploadify.egg-info/SOURCES.txt
django_servee_uploadify.egg-info/dependency_links.txt
django_servee_uploadify.egg-info/not-zip-safe
django_servee_uploadify.egg-info/top_level.txt
servee_uploadify/.DS_Store
servee_uploadify/__init__.py
servee_uploadify/__init__.pyc
servee_uploadify/models.py
servee_uploadify/models.pyc
servee_uploadify/static/.DS_Store
servee_uploadify/static/uploadify/Change Log.txt
servee_uploadify/static/uploadify/check-exists.php
servee_uploadify/static/uploadify/expressInstall.swf
servee_uploadify/static/uploadify/jquery.uploadify-3.1.js
servee_uploadify/static/uploadify/jquery.uploadify-3.1.min.js
servee_uploadify/static/uploadify/jquery.uploadify.3.0.0.min.js
servee_uploadify/static/uploadify/jquery.uploadify.js
servee_uploadify/static/uploadify/license.txt
servee_uploadify/static/uploadify/swfobject.js
servee_uploadify/static/uploadify/uploadify-cancel.png
servee_uploadify/static/uploadify/uploadify.css
servee_uploadify/static/uploadify/uploadify.php
servee_uploadify/static/uploadify/uploadify.swf