Metadata-Version: 1.0
Name: django-servee-uploadify
Version: 0.1
Summary: Uploadify static files for servee
Home-page: http://github.com/servee/servee-uploadify/
Author: Issac Kelly
Author-email: issac@servee.com
License: BSD
Platform: UNKNOWN
Classifier: Development Status :: 3 - Alpha
Classifier: Framework :: Django
Classifier: Intended Audience :: Developers
Classifier: License :: OSI Approved :: BSD License
Classifier: Operating System :: OS Independent
Classifier: Programming Language :: Python
Classifier: Topic :: Internet :: WWW/HTTP
